sparv/__init__.py
sparv/__main__.py
sparv/py.typed
sparv/api/__init__.py
sparv/api/classes.py
sparv/api/util/__init__.py
sparv/api/util/constants.py
sparv/api/util/export.py
sparv/api/util/install.py
sparv/api/util/misc.py
sparv/api/util/mysql_wrapper.py
sparv/api/util/system.py
sparv/api/util/tagsets/__init__.py
sparv/api/util/tagsets/pos_to_upos.py
sparv/api/util/tagsets/suc_to_feats.py
sparv/api/util/tagsets/tagmappings.py
sparv/core/Snakefile
sparv/core/__init__.py
sparv/core/config.py
sparv/core/console.py
sparv/core/io.py
sparv/core/log_handler.py
sparv/core/misc.py
sparv/core/paths.py
sparv/core/plugins.py
sparv/core/preload.py
sparv/core/registry.py
sparv/core/run.py
sparv/core/run_snake.py
sparv/core/schema.py
sparv/core/setup.py
sparv/core/snake_prints.py
sparv/core/snake_utils.py
sparv/core/wizard.py
sparv/core_modules/export/__init__.py
sparv/core_modules/import/__init__.py
sparv/core_modules/metadata/__init__.py
sparv/core_modules/sparv/__init__.py
sparv/modules/conll_export/__init__.py
sparv/modules/conll_export/conllu.py
sparv/modules/conll_export/metadata.yaml
sparv/modules/csv_export/__init__.py
sparv/modules/csv_export/csv_export.py
sparv/modules/cwb/__init__.py
sparv/modules/cwb/cwb.py
sparv/modules/cwb/info.py
sparv/modules/cwb/install_corpus.py
sparv/modules/dateformat/__init__.py
sparv/modules/dateformat/dateformat.py
sparv/modules/docx_import/__init__.py
sparv/modules/docx_import/docx_import.py
sparv/modules/geo/__init__.py
sparv/modules/geo/geo.py
sparv/modules/geo/metadata.yaml
sparv/modules/hist/__init__.py
sparv/modules/hist/diapivot.py
sparv/modules/hist/hist.py
sparv/modules/hist/models.py
sparv/modules/hunpos/__init__.py
sparv/modules/hunpos/hunpos.py
sparv/modules/hunpos/metadata.yaml
sparv/modules/hunpos/morphtable.py
sparv/modules/hunpos/morphtable_hist.py
sparv/modules/korp/__init__.py
sparv/modules/korp/config.py
sparv/modules/korp/lemgram_index.py
sparv/modules/korp/timespan.py
sparv/modules/korp/wordpicture.py
sparv-5.3.1.dist-info/METADATA
sparv-5.3.1.dist-info/WHEEL
sparv-5.3.1.dist-info/entry_points.txt
sparv-5.3.1.dist-info/licenses/LICENSE
sparv-5.3.1.dist-info/RECORD
