Metadata-Version: 2.4
Name: sparv
Version: 5.3.1
Summary: Språkbanken's analysis platform
Project-URL: Homepage, https://github.com/spraakbanken/sparv/
Project-URL: Documentation, https://spraakbanken.gu.se/sparv/
Author-email: Språkbanken Text <sb-info@svenska.gu.se>
License-Expression: MIT
License-File: LICENSE
Requires-Python: >=3.10
Requires-Dist: appdirs==1.4.4
Requires-Dist: argcomplete==3.6.2
Requires-Dist: docx2python==1.27.1
Requires-Dist: jsonschema==4.23.0
Requires-Dist: nltk==3.9.1
Requires-Dist: packaging>=21.0
Requires-Dist: protobuf<4.0.0,>=3.19.0
Requires-Dist: pycountry==24.6.1
Requires-Dist: pypdfium2==4.30.0
Requires-Dist: python-dateutil==2.9.0
Requires-Dist: python-json-logger==3.3.0
Requires-Dist: pyyaml==6.0.2
Requires-Dist: questionary==1.10.0
Requires-Dist: requests>=2.32.3
Requires-Dist: rich-argparse==1.7.0
Requires-Dist: rich==14.0.0
Requires-Dist: snakemake==7.32.3
Requires-Dist: stanza==1.10.1
Requires-Dist: torch>=1.9.1
Requires-Dist: typing-inspect==0.9.0
Provides-Extra: dev
Requires-Dist: bs4; extra == 'dev'
Requires-Dist: mkdocs-github-admonitions-plugin==0.0.3; extra == 'dev'
Requires-Dist: mkdocs-material==9.6.11; extra == 'dev'
Requires-Dist: mkdocstrings-python==1.16.10; extra == 'dev'
Requires-Dist: pandocfilters==1.5.1; extra == 'dev'
Requires-Dist: pytest-sugar>=1.0.0; extra == 'dev'
Requires-Dist: pytest>=8.0.0; extra == 'dev'
Requires-Dist: ruff; extra == 'dev'
